autods_copilot/__init__.py
autods_copilot/agent/__init__.py
autods_copilot/agent/copilot_agent.py
autods_copilot/agent/response_handler.py
autods_copilot/config/__init__.py
autods_copilot/config/default_config.yaml
autods_copilot/config/model_configs.yaml
autods_copilot/interpreter/__init__.py
autods_copilot/interpreter/python_executor.py
autods_copilot/interpreter/security.py
autods_copilot/llm/__init__.py
autods_copilot/llm/openai_adapter.py
autods_copilot/modules/__init__.py
autods_copilot/modules/eda/__init__.py
autods_copilot/modules/eda/analyzer.py
autods_copilot/modules/eda/visualizer.py
autods_copilot/modules/encoding/__init__.py
autods_copilot/modules/encoding/categorical.py
autods_copilot/modules/modeling/__init__.py
autods_copilot/modules/modeling/classifier.py
autods_copilot/modules/modeling/regressor.py
autods_copilot/nlp/__init__.py
autods_copilot/nlp/query_processor.py
autods_copilot/prompts/__init__.py
autods_copilot/prompts/prompt_manager.py
autods_copilot/utils/__init__.py
autods_copilot/utils/config.py
autods_copilot/utils/logger.py
autods_copilot/utils/validators.py
autods_copilot-0.1.0.dist-info/licenses/LICENSE
autods_copilot-0.1.0.dist-info/METADATA
autods_copilot-0.1.0.dist-info/WHEEL
autods_copilot-0.1.0.dist-info/top_level.txt
autods_copilot-0.1.0.dist-info/RECORD
