Metadata-Version: 2.4
Name: autods-copilot
Version: 0.1.0
Summary: GenAI-powered agent-based tool for automated data science workflows
Home-page: https://github.com/MaheshKumarsg036/AutoDS_Copilot
Author: MaheshKumarsg036
Author-email: contact@autods-copilot.com
Maintainer: MaheshKumarsg036
License: MIT License
Project-URL: Homepage, https://github.com/MaheshKumarsg036/AutoDS_Copilot
Project-URL: Documentation, https://github.com/MaheshKumarsg036/AutoDS_Copilot#readme
Project-URL: Repository, https://github.com/MaheshKumarsg036/AutoDS_Copilot.git
Project-URL: Bug Tracker, https://github.com/MaheshKumarsg036/AutoDS_Copilot/issues
Keywords: data-science,machine-learning,artificial-intelligence,automation,gpt,openai,eda,feature-engineering
Classifier: Development Status :: 3 - Alpha
Classifier: Intended Audience :: Developers
Classifier: Intended Audience :: Science/Research
Classifier: License :: OSI Approved :: MIT License
Classifier: Operating System :: OS Independent
Classifier: Programming Language :: Python :: 3
Classifier: Programming Language :: Python :: 3.8
Classifier: Programming Language :: Python :: 3.9
Classifier: Programming Language :: Python :: 3.10
Classifier: Programming Language :: Python :: 3.11
Classifier: Programming Language :: Python :: 3.12
Classifier: Topic :: Scientific/Engineering :: Artificial Intelligence
Classifier: Topic :: Scientific/Engineering :: Information Analysis
Classifier: Topic :: Software Development :: Libraries :: Python Modules
Requires-Python: >=3.8
License-File: LICENSE
Requires-Dist: pandas>=1.3.0
Requires-Dist: numpy>=1.20.0
Requires-Dist: scikit-learn>=1.0.0
Requires-Dist: matplotlib>=3.5.0
Requires-Dist: seaborn>=0.11.0
Requires-Dist: openai>=1.0.0
Requires-Dist: pyyaml>=6.0
Requires-Dist: requests>=2.25.0
Dynamic: author-email
Dynamic: home-page
Dynamic: license-file
Dynamic: requires-python
